no_action/__init__.py
no_action/easy_doc.py
no_action/exceptions.py
no_action/procedure.py
no_action/step.py
no_action/templates/output.conwiki.j2
no_action/templates/output.md.j2
no_action/templates/output.rst.j2
no_action/test_easy_doc.py
no_action-0.8.0.dist-info/COPYING
no_action-0.8.0.dist-info/LICENSE
no_action-0.8.0.dist-info/METADATA
no_action-0.8.0.dist-info/WHEEL
no_action-0.8.0.dist-info/RECORD
