Metadata-Version: 2.1
Name: no_action
Version: 0.8.0
Summary: An incremental automation library to eliminate toil in processes.
Home-page: https://gitlab.com/Skoretz/no_action
License: GPL-3.0-or-later
Keywords: automation
Author: Nicholas Skoretz
Author-email: nskoretz@protonmail.com
Requires-Python: >=3.11,<4.0
Classifier: License :: OSI Approved :: GNU General Public License v3 or later (GPLv3+)
Classifier: Programming Language :: Python :: 3
Classifier: Programming Language :: Python :: 3.11
Classifier: Programming Language :: Python :: 3.12
Requires-Dist: jinja2 (>=3.1.3,<4.0.0)
Requires-Dist: loguru (>=0.7.2,<0.8.0)
Project-URL: Repository, https://gitlab.com/Skoretz/no_action
